access_cli_sealuzh/__init__.py
access_cli_sealuzh/logger.py
access_cli_sealuzh/main.py
access_cli_sealuzh/schema.py
access_cli_sealuzh-0.1.9.dist-info/METADATA
access_cli_sealuzh-0.1.9.dist-info/WHEEL
access_cli_sealuzh-0.1.9.dist-info/entry_points.txt
access_cli_sealuzh-0.1.9.dist-info/licenses/LICENSE.md
access_cli_sealuzh-0.1.9.dist-info/RECORD
