Metadata-Version: 2.4
Name: access_cli_sealuzh
Version: 0.1.9
Summary: Verify ACCESS courses locally
Project-URL: Homepage, https://github.com/mp-access/access_cli
Project-URL: Bug Tracker, https://github.com/mp-access/access_cli/issues
Author-email: Carol Alexandru <alexandru@ifi.uzh.ch>
License-File: LICENSE.md
Classifier: License :: OSI Approved :: MIT License
Classifier: Operating System :: OS Independent
Classifier: Programming Language :: Python :: 3
Requires-Python: >=3.7
Requires-Dist: cerberus~=1.3
Requires-Dist: tomli~=2.0
